anpm/__init__.py
anpm/grid.py
anpm/streaming.py
anpm/tk.py
anpm/wrappers.py
anpm/ygo.py
anpm/ssc_new/__init__.py
anpm/ssc_new/client.py
anpm/ssc_new/server.py
anpm/ssc_new/shared.py
anpm/ssc_old/Client.py
anpm/ssc_old/Server.py
anpm/ssc_old/Shared.py
anpm/ssc_old/__init__.py
anpm_public-0.6.0.dist-info/METADATA
anpm_public-0.6.0.dist-info/WHEEL
anpm_public-0.6.0.dist-info/top_level.txt
anpm_public-0.6.0.dist-info/RECORD
