Metadata-Version: 2.2
Name: anpm-public
Version: 0.6.0
Summary: A collection of scripts by me, Alia. THIS IS THE PUBLIC VERSION, VERSION  NUMBERS MAY BE INACURRATE.
Author: Alia Normal
Author-email: dan.driscoll@aussiebb.com
Classifier: Programming Language :: Python :: 3
Classifier: License :: OSI Approved :: MIT License
Classifier: Operating System :: OS Independent
Requires-Python: >=3.12
Dynamic: author
Dynamic: author-email
Dynamic: classifier
Dynamic: requires-python
Dynamic: summary
